bin/linux_pdfresurrect
bin/mac_pdfresurrect
bin/pdfresurrect.1
pdforensic/__init__.py
pdforensic/check_eof_markers.py
pdforensic/check_versions.py
pdforensic/retrieve_all_versions.py
pdforensic/retrieve_metadata.py
pdforensic/utils.py
pdforensic_authentic_check-0.1.41.data/data/bin/linux_pdfresurrect
pdforensic_authentic_check-0.1.41.data/data/bin/mac_pdfresurrect
pdforensic_authentic_check-0.1.41.data/data/bin/pdfresurrect.1
pdforensic_authentic_check-0.1.41.dist-info/licenses/LICENSE
pdforensic_authentic_check-0.1.41.dist-info/METADATA
pdforensic_authentic_check-0.1.41.dist-info/WHEEL
pdforensic_authentic_check-0.1.41.dist-info/entry_points.txt
pdforensic_authentic_check-0.1.41.dist-info/top_level.txt
pdforensic_authentic_check-0.1.41.dist-info/RECORD
