Metadata-Version: 2.4
Name: pdforensic-authentic-check
Version: 0.1.41
Summary: A simple PDF forensic toolkit using pdfresurrect and bash utilities
Author: Alex Mkwizu
Author-email: alexgmkwizu@gmail.com
License-File: LICENSE
Provides-Extra: dev
Requires-Dist: pytest; extra == "dev"
Dynamic: author
Dynamic: author-email
Dynamic: description
Dynamic: description-content-type
Dynamic: license-file
Dynamic: provides-extra
Dynamic: summary
